soxbindings-1.2.3.dist-info/LICENSE
soxbindings-1.2.3.dist-info/top_level.txt
soxbindings-1.2.3.dist-info/RECORD
soxbindings-1.2.3.dist-info/WHEEL
soxbindings-1.2.3.dist-info/METADATA
soxbindings.libs/libvorbisenc-b5e6dd98.so.2.0.6
soxbindings.libs/libgomp-2716b9e4.so.1.0.0
soxbindings.libs/libsox-70e8e077.so.3.0.0
soxbindings.libs/libogg-ab8c61f4.so.0.6.0
soxbindings.libs/libFLAC-df92054f.so.8.2.0
soxbindings.libs/libvorbisfile-6a53e35b.so.3.3.2
soxbindings.libs/libltdl-6dfde997.so.7.3.1
soxbindings.libs/libmp3lame-38f869d5.so.0.0.0
soxbindings.libs/libmad-bbece157.so.0.2.1
soxbindings.libs/libvorbis-fa167044.so.0.4.3
soxbindings/__init__.py
soxbindings/sox_cli.py
soxbindings/transform.py
soxbindings/audio.py
soxbindings/effects.py
soxbindings/_soxbindings.cpython-35m-i386-linux-gnu.so
