Metadata-Version: 2.1
Name: soxbindings
Version: 1.2.3
Summary: Python bindings for sox.
Home-page: https://github.com/pseeth/soxbindings
Author: Prem Seetharaman
Author-email: prem@u.northwestern.edu
License: UNKNOWN
Platform: UNKNOWN
Requires-Dist: sox (>=1.4.0)
